{
  "project_info": {
    "project_number": "764371836749",
    "firebase_url": "https://test-toonchat.firebaseio.com",
    "project_id": "test-toonchat",
    "storage_bucket": "test-toonchat.appspot.com"
  },
  "client": [
    {
      "client_info": {
        "mobilesdk_app_id": "1:764371836749:android:0c73b793b9757cba",
        "android_client_info": {
          "package_name": "net.testtoonchat"
        }
      },
      "oauth_client": [
        {
          "client_id": "764371836749-4iqlu88on0oq2trnmtj5ts4sc4203bag.apps.googleusercontent.com",
          "client_type": 3
        }
      ],
      "api_key": [
        {
          "current_key": "AIzaSyC4rALpz-7w24gN_cjf5JT8Y6rcC9Qtch8"
        }
      ],
      "services": {
        "analytics_service": {
          "status": 1
        },
        "appinvite_service": {
          "status": 1,
          "other_platform_oauth_client": []
        },
        "ads_service": {
          "status": 2
        }
      }
    }
  ],
  "configuration_version": "1"
}